happycow/__init__.py
happycow/main.py
happycow/saying.py
happycow-0.1.0.dist-info/METADATA
happycow-0.1.0.dist-info/WHEEL
happycow-0.1.0.dist-info/entry_points.txt
happycow-0.1.0.dist-info/RECORD
