Metadata-Version: 2.1
Name: happycow
Version: 0.1.0
Summary: happycow demo
Author: BuxianChen
Author-email: 541205605@qq.com
Requires-Python: >=3.10,<4.0
Classifier: Programming Language :: Python :: 3
Classifier: Programming Language :: Python :: 3.10
Classifier: Programming Language :: Python :: 3.11
Classifier: Programming Language :: Python :: 3.12
